dumpall/__init__.py
dumpall/__version__.py
dumpall/dumper.py
dumpall/addons/__init__.py
dumpall/addons/dsdumper.py
dumpall/addons/gitdumper.py
dumpall/addons/idxdumper.py
dumpall/addons/svndumper.py
dumpall/thirdparty/__init__.py
dumpall/thirdparty/dsstore.py
dumpall/thirdparty/gin.py
dumpall-0.3.2.dist-info/LICENSE
dumpall-0.3.2.dist-info/METADATA
dumpall-0.3.2.dist-info/WHEEL
dumpall-0.3.2.dist-info/entry_points.txt
dumpall-0.3.2.dist-info/top_level.txt
dumpall-0.3.2.dist-info/RECORD
