Metadata-Version: 2.1
Name: dumpall
Version: 0.3.2
Summary: 一款信息泄漏利用工具，适用于.git/.svn/.DS_Store泄漏和目录列出漏洞利用
Home-page: https://github.com/0xHJK/dumpall
Author: HJK
Author-email: HJKdev@gmail.com
License: MIT License
Platform: UNKNOWN
Classifier: Development Status :: 4 - Beta
Classifier: Environment :: Console
Classifier: Intended Audience :: Developers
Classifier: Intended Audience :: End Users/Desktop
Classifier: License :: OSI Approved :: MIT License
Classifier: Natural Language :: Chinese (Simplified)
Classifier: Operating System :: OS Independent
Classifier: Programming Language :: Python
Classifier: Programming Language :: Python :: 3
Classifier: Programming Language :: Python :: 3 :: Only
Classifier: Programming Language :: Python :: 3.7
Classifier: Programming Language :: Python :: 3.8
Classifier: Topic :: Internet
Classifier: Topic :: Internet :: WWW/HTTP
Classifier: Topic :: Security
Classifier: Topic :: Utilities
Requires-Dist: click
Requires-Dist: aiohttp
Requires-Dist: aiomultiprocess
